flake8_single_quotes.py
setup.py
flake8_single_quotes.egg-info/PKG-INFO
flake8_single_quotes.egg-info/SOURCES.txt
flake8_single_quotes.egg-info/dependency_links.txt
flake8_single_quotes.egg-info/entry_points.txt
flake8_single_quotes.egg-info/not-zip-safe
flake8_single_quotes.egg-info/requires.txt
flake8_single_quotes.egg-info/top_level.txt
flake8_single_quotes.egg-info/version_info.json