Metadata-Version: 1.1
Name: flake8-single-quotes
Version: 0.1.0
Summary: A Flake8 extension to enforce single-quotes.
Home-page: https://github.com/maxcountryman/flake8-single-quotes/
Author: Max Countryman
Author-email: maxc@me.com
License: MIT
Platform: UNKNOWN
Classifier: Development Status :: 4 - Beta
Classifier: Environment :: Console
Classifier: Intended Audience :: Developers
Classifier: Operating System :: OS Independent
Classifier: License :: OSI Approved :: MIT License
Classifier: Programming Language :: Python
Classifier: Programming Language :: Python :: 2
Classifier: Programming Language :: Python :: 2.7
Classifier: Programming Language :: Python :: 3
Classifier: Programming Language :: Python :: 3.3
Classifier: Programming Language :: Python :: 3.4
Classifier: Topic :: Software Development :: Quality Assurance
